{
    "Setting":[
               {"name": "Survey notification","discription":""},
                 {"name": "Notification Tone","discription":"Play notification when new notification recevied"},
               {"name": "Show ticker","discription":"Shows snippet of new message in notification bar"},
                {"name": "Vibration","discription":"Vibrate when new message are recevied"},
                {"name": "About","discription":""},
                {"name": "Privacy Policy","discription":""},
                {"name": "Rate Us","discription":""},
                {"name": "Logout","discription":""},
               
               ],
    
   
  "NextVersion":[{"value":["Male","Female"] },{"value":["12 - 17","18 - 25","26 - 35","36 - 50","50 Above"]}],

    
   
   
    
}

